pawel_distribution.py
pawel_distribution-0.0.1.dist-info/LICENSE
pawel_distribution-0.0.1.dist-info/WHEEL
pawel_distribution-0.0.1.dist-info/METADATA
pawel_distribution-0.0.1.dist-info/RECORD
